[{"date":1683705223,"sid":"IVH1AU","account":"0654711705","amount":"15","currency":"USD","gateway":"EDAHAB","txn_type":"DEBIT","merchant_id":4,"txn_detail":"[SifaloPay] Insufficient Balance on PBWALLET, Transfer of $15 requested from EDAHAB Account: #0654711705 Available Balance: $0"},{"date":1683705230,"sid":"XN3VQO","account":"0654711705","amount":"15","currency":"USD","gateway":"EDAHAB","txn_type":"DEBIT","merchant_id":4,"txn_detail":"[SifaloPay] Insufficient Balance on PBWALLET, Transfer of $15 requested from EDAHAB Account: #0654711705 Available Balance: $0"},{"date":1683705254,"sid":"TR284I","account":"0654711705","amount":"15","currency":"USD","gateway":"EDAHAB","txn_type":"DEBIT","merchant_id":4,"txn_detail":"[SifaloPay] Insufficient Balance on PBWALLET, Transfer of $15 requested from EDAHAB Account: #0654711705 Available Balance: $0"}]